[
{"university_name": "CaliforniaInstituteofTechnology", "national_ranking": 1},
{"university_name": "StanfordUniversity", "national_ranking": 2},
{"university_name": "MassachusettsInstituteofTechnology", "national_ranking": 3},
{"university_name": "HarvardUniversity", "national_ranking": 4},
{"university_name": "PrincetonUniversity", "national_ranking": 5},
{"university_name": "UniversityofCaliforniaBerkeley", "national_ranking": 6},
{"university_name": "UniversityofChicago", "national_ranking": 6},
{"university_name": "YaleUniversity", "national_ranking": 8},
{"university_name": "UniversityofPennsylvania", "national_ranking": 9},
{"university_name": "UniversityofCaliforniaLosAngeles", "national_ranking": 10},
{"university_name": "ColumbiaUniversity", "national_ranking": 11},
{"university_name": "JohnsHopkinsUniversity", "national_ranking": 12},
{"university_name": "DukeUniversity", "national_ranking": 13},
{"university_name": "CornellUniversity", "national_ranking": 14},
{"university_name": "NorthwesternUniversity", "national_ranking": 15},
{"university_name": "UniversityofMichigan", "national_ranking": 16},
{"university_name": "CarnegieMellonUniversity", "national_ranking": 17},
{"university_name": "UniversityofWashington", "national_ranking": 18},
{"university_name": "NewYorkUniversity", "national_ranking": 19},
{"university_name": "GeorgiaInstituteofTechnology", "national_ranking": 20},
{"university_name": "UniversityofIllinoisatUrbanaChampaign", "national_ranking": 21},
{"university_name": "UniversityofCaliforniaSanDiego", "national_ranking": 22},
{"university_name": "UniversityofWisconsinMadison", "national_ranking": 23},
{"university_name": "UniversityofCaliforniaSantaBarbara", "national_ranking": 24},
{"university_name": "UniversityofTexasatAustin", "national_ranking": 25},
{"university_name": "BrownUniversity", "national_ranking": 26},
{"university_name": "UniversityofCaliforniaDavis", "national_ranking": 26},
{"university_name": "UniversityofMinnesota", "national_ranking": 28},
{"university_name": "UniversityofNorthCarolinaatChapelHill", "national_ranking": 29},
{"university_name": "WashingtonUniversityinStLouis", "national_ranking": 30},
{"university_name": "UniversityofSouthernCalifornia", "national_ranking": 31},
{"university_name": "BostonUniversity", "national_ranking": 32},
{"university_name": "UniversityofMarylandCollegePark", "national_ranking": 33},
{"university_name": "PennsylvaniaStateUniversity", "national_ranking": 34},
{"university_name": "PurdueUniversity", "national_ranking": 35},
{"university_name": "OhioStateUniversity", "national_ranking": 36},
{"university_name": "UniversityofPittsburgh", "national_ranking": 37},
{"university_name": "DartmouthCollege", "national_ranking": 38},
{"university_name": "EmoryUniversity", "national_ranking": 38},
{"university_name": "RiceUniversity", "national_ranking": 40},
{"university_name": "UniversityofCaliforniaIrvine", "national_ranking": 41},
{"university_name": "MichiganStateUniversity", "national_ranking": 42},
{"university_name": "GeorgetownUniversity", "national_ranking": 43},
{"university_name": "VanderbiltUniversity", "national_ranking": 44},
{"university_name": "UniversityofColoradoBoulder", "national_ranking": 45},
{"university_name": "UniversityofVirginia", "national_ranking": 46},
{"university_name": "CaseWesternReserveUniversity", "national_ranking": 47},
{"university_name": "ArizonaStateUniversity", "national_ranking": 48},
{"university_name": "UniversityofFlorida", "national_ranking": 49},
{"university_name": "TuftsUniversity", "national_ranking": 50},
{"university_name": "RutgerstheStateUniversityofNewJersey", "national_ranking": 51},
{"university_name": "UniversityofNotreDame", "national_ranking": 52},
{"university_name": "UniversityofCaliforniaSantaCruz", "national_ranking": 53},
{"university_name": "IndianaUniversity", "national_ranking": 54},
{"university_name": "UniversityofRochester", "national_ranking": 55},
{"university_name": "UniversityofArizona", "national_ranking": 56},
{"university_name": "UniversityofCaliforniaRiverside", "national_ranking": 57},
{"university_name": "UniversityofMassachusetts", "national_ranking": 57},
{"university_name": "TexasAMUniversity", "national_ranking": 59},
{"university_name": "NortheasternUniversity", "national_ranking": 60},
{"university_name": "UniversityofMiami", "national_ranking": 60},
{"university_name": "BrandeisUniversity", "national_ranking": 62},
{"university_name": "UniversityofIllinoisatChicago", "national_ranking": 63},
{"university_name": "BostonCollege", "national_ranking": 64},
{"university_name": "FloridaStateUniversity", "national_ranking": 64},
{"university_name": "GeorgeWashingtonUniversity", "national_ranking": 64},
{"university_name": "NorthCarolinaStateUniversity", "national_ranking": 64},
{"university_name": "StonyBrookUniversity", "national_ranking": 64},
{"university_name": "UniversityofCincinnati", "national_ranking": 64},
{"university_name": "UniversityofDelaware", "national_ranking": 64},
{"university_name": "UniversityofHawaiiatM\u0101noa", "national_ranking": 64},
{"university_name": "UniversityofIowa", "national_ranking": 64},
{"university_name": "UniversityofSouthFlorida", "national_ranking": 64},
{"university_name": "UniversityofTexasatDallas", "national_ranking": 64},
{"university_name": "UniversityofUtah", "national_ranking": 64},
{"university_name": "WakeForestUniversity", "national_ranking": 64},
{"university_name": "ColoradoSchoolofMines", "national_ranking": 77},
{"university_name": "OregonHealthandScienceUniversity", "national_ranking": 77},
{"university_name": "RensselaerPolytechnicInstitute", "national_ranking": 77},
{"university_name": "RushUniversity", "national_ranking": 77},
{"university_name": "SyracuseUniversity", "national_ranking": 77},
{"university_name": "UniversityatBuffalo", "national_ranking": 77},
{"university_name": "UniversityofTennesseeKnoxville", "national_ranking": 77},
{"university_name": "VirginiaPolytechnicInstituteandStateUniversity", "national_ranking": 77},
{"university_name": "WilliamMary", "national_ranking": 77},
{"university_name": "ClarkUniversity", "national_ranking": 86},
{"university_name": "ColoradoStateUniversity", "national_ranking": 86},
{"university_name": "GeorgeMasonUniversity", "national_ranking": 86},
{"university_name": "OregonStateUniversity", "national_ranking": 86},
{"university_name": "SaintLouisUniversity", "national_ranking": 86},
{"university_name": "TempleUniversity", "national_ranking": 86},
{"university_name": "UniversityofAlaskaFairbanks", "national_ranking": 86},
{"university_name": "UniversityofConnecticut", "national_ranking": 86},
{"university_name": "UniversityofDenver", "national_ranking": 86},
{"university_name": "UniversityofGeorgia", "national_ranking": 86},
{"university_name": "UniversityofNebraskaLincoln", "national_ranking": 86},
{"university_name": "UniversityofOregon", "national_ranking": 86},
{"university_name": "BinghamtonUniversityStateUniversityofNewYork", "national_ranking": 98},
{"university_name": "DrexelUniversity", "national_ranking": 98},
{"university_name": "IowaStateUniversity", "national_ranking": 98},
{"university_name": "TulaneUniversity", "national_ranking": 98},
{"university_name": "UniversityofHouston", "national_ranking": 98},
{"university_name": "UniversityofKansas", "national_ranking": 98},
{"university_name": "UniversityofKent", "national_ranking": 98},
{"university_name": "UniversityofMissouri", "national_ranking": 98},
{"university_name": "UniversityofOklahoma", "national_ranking": 98},
{"university_name": "UniversityofTexasatSanAntonio", "national_ranking": 98},
{"university_name": "WashingtonStateUniversity", "national_ranking": 98},
{"university_name": "WayneStateUniversity", "national_ranking": 98},
{"university_name": "AmericanUniversity", "national_ranking": 110},
{"university_name": "FloridaInternationalUniversity", "national_ranking": 110},
{"university_name": "GeorgiaStateUniversity", "national_ranking": 110},
{"university_name": "KentStateUniversity", "national_ranking": 110},
{"university_name": "LehighUniversity", "national_ranking": 110},
{"university_name": "NewMexicoStateUniversity", "national_ranking": 110},
{"university_name": "NorthernArizonaUniversity", "national_ranking": 110},
{"university_name": "SanDiegoStateUniversity", "national_ranking": 110},
{"university_name": "StevensInstituteofTechnology", "national_ranking": 110},
{"university_name": "UniversityofMary", "national_ranking": 110},
{"university_name": "UniversityofMontana", "national_ranking": 110},
{"university_name": "CreightonUniversity", "national_ranking": 121},
{"university_name": "KansasStateUniversity", "national_ranking": 121},
{"university_name": "LouisianaStateUniversity", "national_ranking": 121},
{"university_name": "MissouriUniversityofScienceandTechnology", "national_ranking": 121},
{"university_name": "MontanaStateUniversity", "national_ranking": 121},
{"university_name": "NewJerseyInstituteofTechnology", "national_ranking": 121},
{"university_name": "OklahomaStateUniversity", "national_ranking": 121},
{"university_name": "OldDominionUniversity", "national_ranking": 121},
{"university_name": "StateUniversityofNewYorkAlbany", "national_ranking": 121},
{"university_name": "UniversityofArkansas", "national_ranking": 121},
{"university_name": "UniversityofNebraskaMedicalCenter", "national_ranking": 121},
{"university_name": "UniversityofTexasatArlington", "national_ranking": 121},
{"university_name": "UniversityofToledo", "national_ranking": 121},
{"university_name": "UniversityofTulsa", "national_ranking": 121},
{"university_name": "UniversityofWisconsin", "national_ranking": 121},
{"university_name": "AuburnUniversity", "national_ranking": 136},
{"university_name": "ClemsonUniversity", "national_ranking": 136},
{"university_name": "FloridaInstituteofTechnology", "national_ranking": 136},
{"university_name": "HofstraUniversity", "national_ranking": 136},
{"university_name": "MiamiUniversity", "national_ranking": 136},
{"university_name": "OaklandUniversity", "national_ranking": 136},
{"university_name": "OhioUniversity", "national_ranking": 136},
{"university_name": "RochesterInstituteofTechnology", "national_ranking": 136},
{"university_name": "TexasTechUniversity", "national_ranking": 136},
{"university_name": "UniversityofNorthCarolinaatGreensboro", "national_ranking": 136},
{"university_name": "UniversityofTexasatElPaso", "national_ranking": 136},
{"university_name": "EmbryRiddleAeronauticalUniversity", "national_ranking": 147},
{"university_name": "UniversityofSouthernMississippi", "national_ranking": 147}
]